{
  "version": 3,
  "configurePresets": [
    {
      "name": "Qt-Debug",
      "inherits": "Qt-Default",
      "binaryDir": "${sourceDir}/out/build",
      "cacheVariables": {
        "CMAKE_BUILD_TYPE": "Debug",
        "CMAKE_CXX_FLAGS": "-DQT_QML_DEBUG"
      }
    },
    {
      "name": "Qt-Release",
      "inherits": "Qt-Default",
      "binaryDir": "${sourceDir}/out/build",
      "cacheVariables": {
        "CMAKE_BUILD_TYPE": "Release"
      }
    },
    {
      "hidden": true,
      "name": "Qt-Default",
      "inherits": "5.15.16",
      "vendor": {
        "qt-project.org/Default": {
          "checksum": "+PpANqfHhPmb0qwUNfQJ96Cvvh4="
        }
      }
    },
    {
      "hidden": true,
      "name": "5.15.16",
      "inherits": "Qt",
      "environment": {
        "QTDIR": "C:/QT/5.15.16/MSVC2019_64"
      },
      "architecture": {
        "strategy": "external",
        "value": "x64"
      },
      "generator": "Ninja",
      "vendor": {
        "qt-project.org/Version": {
          "checksum": "cAFNjY4PVQqSyFMZPjkGiNl0x1c="
        }
      }
    }
  ],
  "vendor": {
    "qt-project.org/Presets": {
      "checksum": "C3YWDNCrWuDiWKngx4KIp8xkYvs="
    }
  }
}